PyForce01/__init__.py
PyForce01-1.0.7.dist-info/LICENSE.txt
PyForce01-1.0.7.dist-info/METADATA
PyForce01-1.0.7.dist-info/WHEEL
PyForce01-1.0.7.dist-info/top_level.txt
PyForce01-1.0.7.dist-info/RECORD
