Metadata-Version: 2.1
Name: PyForce01
Version: 1.0.7
Summary: You already know.
Home-page: https://github.com/GrandMoff100/MathFunctions
Author: Quantum_Wizard
Author-email: minecraftcrusher100@gmail.com
License: UNKNOWN
Platform: UNKNOWN
Classifier: Programming Language :: Python :: 3
Classifier: License :: OSI Approved :: MIT License
Requires-Python: >=3.6
